pydeepchainmap/README.MD
pydeepchainmap/__init__.py
pydeepchainmap/requirements.txt
pydeepchainmap/thirdparty.json
pydeepchainmap-0.10.dist-info/LICENSE.rst
pydeepchainmap-0.10.dist-info/METADATA
pydeepchainmap-0.10.dist-info/WHEEL
pydeepchainmap-0.10.dist-info/top_level.txt
pydeepchainmap-0.10.dist-info/RECORD
