Metadata-Version: 2.1
Name: pydeepchainmap
Version: 0.10
Summary: DeepChainMap from the Python documentation
Home-page: https://github.com/hansalemaos/pydeepchainmap
Author: Johannes Fischer
Author-email: aulasparticularesdealemaosp@gmail.com
License: MIT
Keywords: ChainMap
Classifier: Development Status :: 4 - Beta
Classifier: Programming Language :: Python :: 3 :: Only
Classifier: Programming Language :: Python :: 3.10
Classifier: Topic :: Software Development :: Libraries :: Python Modules
Classifier: Topic :: Utilities
License-File: LICENSE.rst
